project/.DS_Store
project/__init__.py
project/__init__.pyc
project/cert.py
project/cert.pyc
project/douyin.py
project/douyin.pyc
project/exception.py
project/exception.pyc
project/model.py
project/model.pyc
project/package.py
project/package.pyc
project/pull.py
project/pull.pyc
tests/.DS_Store
tests/__init__.py
tests/__init__.pyc
tests/api_test.py
tests/api_test.pyc
tests/common_test.py
tests/common_test.pyc
tests/package_test.py
tests/package_test.pyc
tests/test_api.py
tests/test_api.pyc
xyscript/.DS_Store
xyscript/CommonScript.py
xyscript/CommonScript.pyc
xyscript/__init__.py
xyscript/__init__.pyc
xyscript/__main__.py
xyscript/__main__.pyc
xyscript/api.py
xyscript/api.pyc
xyscript/cert.py
xyscript/cert.pyc
xyscript/config.ini
xyscript/config.py
xyscript/config.pyc
xyscript/globalvar.py
xyscript/globalvar.pyc
xyscript/iosProjectTool.py
xyscript/iosProjectTool.pyc
xyscript/package.py
xyscript/xylog.py
xyscript/xylog.pyc
xyscript/common/.DS_Store
xyscript/common/__init__.py
xyscript/common/__init__.pyc
xyscript/common/common.py
xyscript/common/common.pyc
xyscript/common/extension.py
xyscript/common/extension.pyc
xyscript/common/file.py
xyscript/common/interaction.py
xyscript/common/interaction.pyc
xyscript/common/mail.py
xyscript/common/mail.pyc
xyscript/common/sysenv.py
xyscript/common/sysenv.pyc
xyscript/common/threadpool.py
xyscript/common/threadpool.pyc
xyscript/common/timeusage.py
xyscript/common/timeusage.pyc
xyscript/package/__init__.py
xyscript/package/package_pcython.py
xyscript/packagePB/__init__.py
xyscript/packagePB/package.py
xyscript/scripts/.DS_Store
xyscript/scripts/__init__.py
xyscript/scripts/__init__.pyc
xyscript/scripts/xyscript.py
xyscript/scripts/xyscript.pyc
xyscript-0.3.5.dist-info/LICENSE
xyscript-0.3.5.dist-info/METADATA
xyscript-0.3.5.dist-info/WHEEL
xyscript-0.3.5.dist-info/entry_points.txt
xyscript-0.3.5.dist-info/top_level.txt
xyscript-0.3.5.dist-info/RECORD
